addonfactory_splunk_conf_parser_lib.py
addonfactory_splunk_conf_parser_lib-1.0.0.dist-info/LICENSE
addonfactory_splunk_conf_parser_lib-1.0.0.dist-info/METADATA
addonfactory_splunk_conf_parser_lib-1.0.0.dist-info/WHEEL
addonfactory_splunk_conf_parser_lib-1.0.0.dist-info/RECORD
